showcert/__about__.py
showcert/__init__.py
showcert/exceptions.py
showcert/getremote.py
showcert/printcert.py
showcert/processcert.py
showcert/utils.py
showcert/verifychain.py
showcert/cli/gencert_main.py
showcert/cli/showcert_main.py
showcert-0.4.12.dist-info/METADATA
showcert-0.4.12.dist-info/WHEEL
showcert-0.4.12.dist-info/entry_points.txt
showcert-0.4.12.dist-info/licenses/LICENSE
showcert-0.4.12.dist-info/RECORD
