Metadata-Version: 2.4
Name: showcert
Version: 0.4.12
Summary: Simple OpenSSL for humans: all you need for X.509 TLS certificates (and nothing more)
Project-URL: Homepage, https://github.com/yaroslaff/showcert
Project-URL: Issues, https://github.com/yaroslaff/showcert/issues
Author-email: Yaroslav Polyakov <yaroslaff@gmail.com>
License: MIT License
License-File: LICENSE
Keywords: CA,SSL,TLS,X.509,X509,alternative,certificate,gencert,generate,local,openssl,remote,showcert,simple,verify
Classifier: License :: OSI Approved :: MIT License
Classifier: Operating System :: OS Independent
Classifier: Programming Language :: Python :: 3
Classifier: Programming Language :: Python :: 3.8
Classifier: Programming Language :: Python :: 3.9
Classifier: Programming Language :: Python :: 3.10
Classifier: Programming Language :: Python :: 3.11
Classifier: Programming Language :: Python :: 3.12
Classifier: Topic :: Security :: Cryptography
Requires-Python: >=3.8
Requires-Dist: certifi>=2018.10.15
Requires-Dist: cryptography>=41.0.0
Requires-Dist: pem>=23.1.0
Requires-Dist: pyopenssl>=24.0.0
Requires-Dist: python-magic
